vigrep/__init__.py
vigrep/__main__.py
vigrep-0.1.dist-info/entry_points.txt
vigrep-0.1.dist-info/LICENSE
vigrep-0.1.dist-info/WHEEL
vigrep-0.1.dist-info/METADATA
vigrep-0.1.dist-info/RECORD
