Metadata-Version: 2.1
Name: vigrep
Version: 0.1
Summary: Searches through text contained in LabVIEW VI files in a specified directory
License: MIT
Author: strainmike
Requires-Python: >=3.7.0,<4.0.0
Classifier: License :: OSI Approved :: MIT License
Classifier: Programming Language :: Python :: 3
Classifier: Programming Language :: Python :: 3.10
Classifier: Programming Language :: Python :: 3.7
Classifier: Programming Language :: Python :: 3.8
Classifier: Programming Language :: Python :: 3.9
Requires-Dist: pylabview (>=0.1,<0.2)
Requires-Dist: tqdm (>=4.64.0,<5.0.0)
